LICENSE.txt
MANIFEST.in
README.md
setup.cfg
setup.py
./README.md
_/ipydrawio/package.json
_/ipydrawio-jupyter-templates/package.json
_/ipydrawio-jupyter-templates/schemas/@deathbeds/ipydrawio-jupyter-templates/package.json.orig
_/ipydrawio-jupyter-templates/static/480.52b62b9b58b7e8f266d8.js
_/ipydrawio-jupyter-templates/static/568.856f3070f20da1910f5c.js
_/ipydrawio-jupyter-templates/static/remoteEntry.44769bd31cfa74438d49.js
_/ipydrawio-jupyter-templates/static/style.js
_/ipydrawio-jupyter-templates/static/third-party-licenses.json
_/ipydrawio-jupyter-templates/static/tmpl/JupyterLab Mockups.dio
_/ipydrawio-jupyter-templates/static/tmpl/JupyterLab Mockups.png
_/ipydrawio-notebook/package.json
_/ipydrawio-notebook/static/305.2a78373877027398b94d.js
_/ipydrawio-notebook/static/568.bf62ff8767bdb336c364.js
_/ipydrawio-notebook/static/remoteEntry.3ed21b315630d7fbcbd8.js
_/ipydrawio-notebook/static/style.js
_/ipydrawio-notebook/static/third-party-licenses.json
_/ipydrawio-webpack/package.json
_/ipydrawio-webpack/static/480.847ef747812ad1b9ad7d.js
_/ipydrawio-webpack/static/568.686faa5fb0235a20a809.js
_/ipydrawio-webpack/static/remoteEntry.a6261c925e5500117271.js
_/ipydrawio-webpack/static/style.js
_/ipydrawio-webpack/static/third-party-licenses.json
_/ipydrawio-webpack/static/dio/clear.html
_/ipydrawio-webpack/static/dio/disableUpdate.js
_/ipydrawio-webpack/static/dio/export-fonts.css
_/ipydrawio-webpack/static/dio/export3.html
_/ipydrawio-webpack/static/dio/favicon.ico
_/ipydrawio-webpack/static/dio/index.html
_/ipydrawio-webpack/static/dio/open.html
_/ipydrawio-webpack/static/dio/shortcuts.svg
_/ipydrawio-webpack/static/dio/images/1x1.png
_/ipydrawio-webpack/static/dio/images/2x2.png
_/ipydrawio-webpack/static/dio/images/3x3.png
_/ipydrawio-webpack/static/dio/images/ajax-loader.gif
_/ipydrawio-webpack/static/dio/images/all-diagrams-sel.svg
_/ipydrawio-webpack/static/dio/images/all-diagrams.svg
_/ipydrawio-webpack/static/dio/images/android-chrome-192x192.png
src/ipydrawio.egg-info/PKG-INFO
src/ipydrawio.egg-info/SOURCES.txt
src/ipydrawio.egg-info/dependency_links.txt
src/ipydrawio.egg-info/entry_points.txt
src/ipydrawio.egg-info/not-zip-safe
src/ipydrawio.egg-info/requires.txt
src/ipydrawio.egg-info/top_level.txt
